terminis/__init__.py
terminis/__main__.py
terminis/music.sh
terminis/terminis.py
terminis-0.2.4.3.dist-info/LICENSE
terminis-0.2.4.3.dist-info/METADATA
terminis-0.2.4.3.dist-info/WHEEL
terminis-0.2.4.3.dist-info/entry_points.txt
terminis-0.2.4.3.dist-info/RECORD
